odoo/addons/stock_picking_report_salesperson/README.rst
odoo/addons/stock_picking_report_salesperson/__init__.py
odoo/addons/stock_picking_report_salesperson/__manifest__.py
odoo/addons/stock_picking_report_salesperson/i18n/es.po
odoo/addons/stock_picking_report_salesperson/i18n/it.po
odoo/addons/stock_picking_report_salesperson/i18n/stock_picking_report_salesperson.pot
odoo/addons/stock_picking_report_salesperson/readme/CONTRIBUTORS.md
odoo/addons/stock_picking_report_salesperson/readme/DESCRIPTION.md
odoo/addons/stock_picking_report_salesperson/readme/USAGE.md
odoo/addons/stock_picking_report_salesperson/report/report_deliveryslip.xml
odoo/addons/stock_picking_report_salesperson/report/report_stockpicking_operations.xml
odoo/addons/stock_picking_report_salesperson/static/description/icon.png
odoo/addons/stock_picking_report_salesperson/static/description/index.html
odoo_addon_stock_picking_report_salesperson-18.0.1.0.0.2.dist-info/METADATA
odoo_addon_stock_picking_report_salesperson-18.0.1.0.0.2.dist-info/WHEEL
odoo_addon_stock_picking_report_salesperson-18.0.1.0.0.2.dist-info/top_level.txt
odoo_addon_stock_picking_report_salesperson-18.0.1.0.0.2.dist-info/RECORD
